README.md
setup.py
kunci/__init__.py
kunci/kunci.py
kunci.egg-info/PKG-INFO
kunci.egg-info/SOURCES.txt
kunci.egg-info/dependency_links.txt
kunci.egg-info/entry_points.txt
kunci.egg-info/not-zip-safe
kunci.egg-info/top_level.txt