Metadata-Version: 1.0
Name: kunci
Version: 0.1
Summary: Random password generator - To prevent annoying password restriction
Home-page: http://github.com/rustyworks/kunci
Author: rustyworks
Author-email: tristanto.kurniawan@gmail.com
License: MIT
Platform: UNKNOWN
